Itzuli/Api.py
Itzuli/__init__.py
Itzuli-1.1.0.dist-info/LICENSE
Itzuli-1.1.0.dist-info/METADATA
Itzuli-1.1.0.dist-info/WHEEL
Itzuli-1.1.0.dist-info/top_level.txt
Itzuli-1.1.0.dist-info/RECORD
