Metadata-Version: 2.1
Name: Itzuli
Version: 1.1.0
Summary: Itzuli API library
Home-page: https://github.com/Vicomtech/itzuli-api-lib/
Author: Vicomtech
Author-email: posdig-dev@vicomtech.org
License: UNKNOWN
Platform: UNKNOWN
Classifier: Programming Language :: Python :: 3
Classifier: License :: OSI Approved :: GNU General Public License v3 (GPLv3)
Classifier: Operating System :: OS Independent
Requires-Python: >=3.6
License-File: LICENSE
